cached_property_with_invalidation/__init__.py
cached_property_with_invalidation/cached_property_with_invalidation.py
cached_property_with_invalidation-0.0.2.dist-info/LICENSE
cached_property_with_invalidation-0.0.2.dist-info/METADATA
cached_property_with_invalidation-0.0.2.dist-info/WHEEL
cached_property_with_invalidation-0.0.2.dist-info/top_level.txt
cached_property_with_invalidation-0.0.2.dist-info/RECORD
