Metadata-Version: 2.1
Name: cached-property-with-invalidation
Version: 0.0.2
Summary: Decorator to create cached_property that can be invalidated when invalidation variable is updated
Home-page: https://github.com/tylerlum/cached_property_with_invalidation
Author: Tyler Lum
Author-email: tylergwlum@gmail.com
Keywords: python,cached_property,cached,property,invalidation
Classifier: Intended Audience :: Developers
Classifier: Topic :: Software Development :: Libraries
Classifier: Operating System :: OS Independent
Classifier: Programming Language :: Python :: 3
License-File: LICENSE
